M2Crypto/ASN1.py
M2Crypto/AuthCookie.py
M2Crypto/BIO.py
M2Crypto/BN.py
M2Crypto/DH.py
M2Crypto/DSA.py
M2Crypto/EC.py
M2Crypto/EVP.py
M2Crypto/Err.py
M2Crypto/RC4.py
M2Crypto/RSA.py
M2Crypto/Rand.py
M2Crypto/SMIME.py
M2Crypto/X509.py
M2Crypto/__init__.py
M2Crypto/_m2crypto.cp311-win_amd64.pyd
M2Crypto/_m2crypto.pyi
M2Crypto/callback.py
M2Crypto/ftpslib.py
M2Crypto/httpslib.py
M2Crypto/m2.py
M2Crypto/m2crypto.py
M2Crypto/m2urllib.py
M2Crypto/m2urllib2.py
M2Crypto/m2xmlrpclib.py
M2Crypto/py.typed
M2Crypto/threading.py
M2Crypto/types.py
M2Crypto/util.py
M2Crypto/SSL/Checker.py
M2Crypto/SSL/Cipher.py
M2Crypto/SSL/Connection.py
M2Crypto/SSL/Context.py
M2Crypto/SSL/SSLError.py
M2Crypto/SSL/SSLServer.py
M2Crypto/SSL/Session.py
M2Crypto/SSL/TwistedProtocolWrapper.py
M2Crypto/SSL/__init__.py
M2Crypto/SSL/cb.py
M2Crypto/SSL/timeout.py
m2crypto-0.46.0.dist-info/METADATA
m2crypto-0.46.0.dist-info/WHEEL
m2crypto-0.46.0.dist-info/top_level.txt
m2crypto-0.46.0.dist-info/RECORD
