Metadata-Version: 2.4
Name: M2Crypto
Version: 0.46.0
Summary: A Python crypto and SSL toolkit
Author: Ng Pheng Siong
Author-email: ngps@sandbox.rulemaker.net
Maintainer: Matej Cepl
Maintainer-email: mcepl@cepl.eu
License: BSD-2-Clause
Project-URL: home_page, https://sr.ht/~mcepl/m2crypto/
Project-URL: source, https://git.sr.ht/~mcepl/m2crypto
Project-URL: documentation, https://m2crypto.readthedocs.io/en/latest/
Project-URL: report, https://lists.sr.ht/~mcepl/m2crypto
Project-URL: changelog, https://git.sr.ht/~mcepl/m2crypto/tree/master/item/CHANGES
Keywords: cryptography,openssl
Classifier: Development Status :: 5 - Production/Stable
Classifier: Intended Audience :: Developers
Classifier: Operating System :: OS Independent
Classifier: Programming Language :: C
Classifier: Programming Language :: Python
Classifier: Topic :: Security :: Cryptography
Classifier: Topic :: Software Development :: Libraries :: Python Modules
Classifier: Programming Language :: Python :: 3
Classifier: Programming Language :: Python :: 3.6
Classifier: Programming Language :: Python :: 3.7
Classifier: Programming Language :: Python :: 3.8
Classifier: Programming Language :: Python :: 3.9
Classifier: Programming Language :: Python :: 3.10
Classifier: Programming Language :: Python :: 3.11
Classifier: Programming Language :: Python :: 3.12
